{
    "train_csv": "/root/ChanceVitMult/CheXpert-v1.0/train.csv",
    "dev_csv": "/root/ChanceVitMult/CheXpert-v1.0/valid.csv",
    "backbone": "ViT",
    "width": 512,
    "height": 512,
    "dim": 512, 
    "pretrained": "False",
    "dim_feedforward": 2048,
    "in_channels": 1,
    "stochastic_depth": 0.1,
    "batch_size": 16,
    "bias": "False",
    "qk_norm": "True",
    "activation": "relu2",
    "gate_activation": "None",
    "patch_size" : [16,16],
    "num_classes" : 5,
    "dropout" : 0.1,
    "depth": 15,
    "enhance_index": [2,6],
    "enhance_times": 1,
    "nhead" : 8,
    "share_layers": "False",
    "pool_type": "avg",
    "target_shape": [512, 512]
}